{
    "id": "xpl",
    "name": "xPL",
    "description": {
        "fr_FR": "Plugin pour gerer des équipements xPL",
        "en_US": "Plugin to manage xPL equipment"
    },
    "licence": "AGPL",
    "author": "Loïc",
    "require": "4.4",
    "category": "automation protocol",
    "hasOwnDeamon": true,
    "hasDependency": false,
    "changelog": "",
    "documentation": "https:\/\/doc.jeedom.com\/#language#\/",
    "language": [
        "fr_FR",
        "en_US"
    ],
    "compatibility": [
        "rpi",
        "diy",
        "mobile",
        "v4"
    ]
}
